LICENSE
README.md
pyproject.toml
setup.py
latexofme/__init__.py
latexofme/latex_set.py
latexofme.egg-info/PKG-INFO
latexofme.egg-info/SOURCES.txt
latexofme.egg-info/dependency_links.txt
latexofme.egg-info/not-zip-safe
latexofme.egg-info/requires.txt
latexofme.egg-info/top_level.txt