Metadata-Version: 2.4
Name: latexofme
Version: 0.1.0
Summary: LaTeX formatting utilities for scientific notation in Jupyter notebooks
Home-page: https://github.com/SOYONAOC/latexofme
Author: Hajime Hinata
Author-email: Hajime Hinata <onmyojiflow@gmail.com>
License: MIT
Project-URL: Homepage, https://github.com/SOYONAOC/latexofme
Project-URL: Repository, https://github.com/SOYONAOC/latexofme
Project-URL: Bug Reports, https://github.com/SOYONAOC/latexofme/issues
Project-URL: Documentation, https://github.com/SOYONAOC/latexofme#readme
Keywords: latex,scientific-notation,jupyter,formatting,math,display
Classifier: Development Status :: 3 - Alpha
Classifier: Intended Audience :: Science/Research
Classifier: Intended Audience :: Education
Classifier: License :: OSI Approved :: MIT License
Classifier: Operating System :: OS Independent
Classifier: Programming Language :: Python :: 3
Classifier: Programming Language :: Python :: 3.7
Classifier: Programming Language :: Python :: 3.8
Classifier: Programming Language :: Python :: 3.9
Classifier: Programming Language :: Python :: 3.10
Classifier: Programming Language :: Python :: 3.11
Classifier: Programming Language :: Python :: 3.12
Classifier: Topic :: Scientific/Engineering
Classifier: Topic :: Text Processing :: Markup :: LaTeX
Classifier: Topic :: Software Development :: Libraries :: Python Modules
Requires-Python: >=3.7
License-File: LICENSE
Requires-Dist: ipython>=7.0.0
Provides-Extra: dev
Requires-Dist: pytest>=6.0; extra == "dev"
Requires-Dist: pytest-cov>=2.0; extra == "dev"
Requires-Dist: black>=21.0; extra == "dev"
Requires-Dist: flake8>=3.8; extra == "dev"
Requires-Dist: mypy>=0.800; extra == "dev"
Requires-Dist: jupyter>=1.0.0; extra == "dev"
Dynamic: author
Dynamic: home-page
Dynamic: license-file
Dynamic: requires-python
